odoo/addons/hr_holidays_notify_employee_manager/README.rst
odoo/addons/hr_holidays_notify_employee_manager/__init__.py
odoo/addons/hr_holidays_notify_employee_manager/__manifest__.py
odoo/addons/hr_holidays_notify_employee_manager/i18n/ar.po
odoo/addons/hr_holidays_notify_employee_manager/i18n/cs_CZ.po
odoo/addons/hr_holidays_notify_employee_manager/i18n/de.po
odoo/addons/hr_holidays_notify_employee_manager/i18n/es.po
odoo/addons/hr_holidays_notify_employee_manager/i18n/fa.po
odoo/addons/hr_holidays_notify_employee_manager/i18n/fi.po
odoo/addons/hr_holidays_notify_employee_manager/i18n/fr.po
odoo/addons/hr_holidays_notify_employee_manager/i18n/fr_CH.po
odoo/addons/hr_holidays_notify_employee_manager/i18n/hr.po
odoo/addons/hr_holidays_notify_employee_manager/i18n/hr_HR.po
odoo/addons/hr_holidays_notify_employee_manager/i18n/hr_holidays_notify_employee_manager.pot
odoo/addons/hr_holidays_notify_employee_manager/i18n/it.po
odoo/addons/hr_holidays_notify_employee_manager/i18n/lt.po
odoo/addons/hr_holidays_notify_employee_manager/i18n/nl_NL.po
odoo/addons/hr_holidays_notify_employee_manager/i18n/pt_BR.po
odoo/addons/hr_holidays_notify_employee_manager/i18n/ro.po
odoo/addons/hr_holidays_notify_employee_manager/i18n/sl.po
odoo/addons/hr_holidays_notify_employee_manager/models/__init__.py
odoo/addons/hr_holidays_notify_employee_manager/models/hr_leave.py
odoo/addons/hr_holidays_notify_employee_manager/models/res_company.py
odoo/addons/hr_holidays_notify_employee_manager/models/res_config_settings.py
odoo/addons/hr_holidays_notify_employee_manager/readme/CONFIGURE.rst
odoo/addons/hr_holidays_notify_employee_manager/readme/CONTRIBUTORS.rst
odoo/addons/hr_holidays_notify_employee_manager/readme/DESCRIPTION.rst
odoo/addons/hr_holidays_notify_employee_manager/readme/USAGE.rst
odoo/addons/hr_holidays_notify_employee_manager/static/description/icon.png
odoo/addons/hr_holidays_notify_employee_manager/static/description/index.html
odoo12_addon_hr_holidays_notify_employee_manager-12.0.1.1.0.dist-info/METADATA
odoo12_addon_hr_holidays_notify_employee_manager-12.0.1.1.0.dist-info/WHEEL
odoo12_addon_hr_holidays_notify_employee_manager-12.0.1.1.0.dist-info/top_level.txt
odoo12_addon_hr_holidays_notify_employee_manager-12.0.1.1.0.dist-info/RECORD
